rnamining/__init__.py
rnamining/arff_creator.py
rnamining/model_train.py
rnamining/rnamining.py
rnamining/models/coding_prediction/Anolis_carolinensis.pkl
rnamining/models/coding_prediction/Chrysemys_picta_bellii.pkl
rnamining/models/coding_prediction/Crocodylus_porosus.pkl
rnamining/models/coding_prediction/Danio_rerio.pkl
rnamining/models/coding_prediction/Eptatretus_burgeri.pkl
rnamining/models/coding_prediction/Gallus_gallus.pkl
rnamining/models/coding_prediction/Homo_sapiens.pkl
rnamining/models/coding_prediction/Latimeria_chalumnae.pkl
rnamining/models/coding_prediction/Monodelphis_domestica.pkl
rnamining/models/coding_prediction/Mus_musculus.pkl
rnamining/models/coding_prediction/Notechis_scutatus.pkl
rnamining/models/coding_prediction/Ornithorhynchus_anatinus.pkl
rnamining/models/coding_prediction/Petromyzon_marinus.pkl
rnamining/models/coding_prediction/Sphenodon_punctatus.pkl
rnamining/models/coding_prediction/Xenopus_tropicalis.pkl
rnamining/models/coding_prediction/__init__.py
rnamining-1.0.4.data/scripts/rnamining
rnamining-1.0.4.dist-info/LICENSE
rnamining-1.0.4.dist-info/METADATA
rnamining-1.0.4.dist-info/WHEEL
rnamining-1.0.4.dist-info/top_level.txt
rnamining-1.0.4.dist-info/RECORD
